sparql_endpoint_fixture/__init__.py
sparql_endpoint_fixture/endpoint.py
tests/__init__.py
tests/conftest.py
tests/test_endpoint.py
tests/test_errors.py
tests/test_multiple_graphs.py
tests/test_predefined.py
sparql_endpoint_fixture-1.0.1.dist-info/LICENSE
sparql_endpoint_fixture-1.0.1.dist-info/METADATA
sparql_endpoint_fixture-1.0.1.dist-info/WHEEL
sparql_endpoint_fixture-1.0.1.dist-info/top_level.txt
sparql_endpoint_fixture-1.0.1.dist-info/RECORD
