Metadata-Version: 2.1
Name: sparql-endpoint-fixture
Version: 1.0.1
Summary: SPARQL Endpoint Fixture
Home-page: https://github.com/sa-bpelakh/sparql-endpoint-fixture
Author: Boris Pelakh
Author-email: boris.pelakh@semanticarts.com
License: bsd-3-clause
Platform: any
Classifier: Development Status :: 5 - Production/Stable
Classifier: Programming Language :: Python
Classifier: Programming Language :: Python :: 3
Classifier: Programming Language :: Python :: 3.9
Classifier: License :: OSI Approved :: BSD License
Classifier: Topic :: Software Development :: Libraries :: Python Modules
Classifier: Operating System :: OS Independent
Classifier: Natural Language :: English
Requires-Python: >=3.9
Requires-Dist: rdflib >=6.2.0
Requires-Dist: SPARQLWrapper ~=1.8.5
Requires-Dist: requests >=2.22.0
Requires-Dist: pytest >=7.0.0
Requires-Dist: httpretty ~=1.1.3
